Workbook

Sheet Параметры и допущения
A1: Централизованная телефония на Asterisk: центр в московском ЦОД, выносы по городам
A2: Параметры расчёта. Все прочие листы считают от этих значений — меняйте здесь, а не в самом плане.
A4: Показатель | B4: Значение | C4: Откуда взято
A5: ОСНОВАНИЕ | B5: протокол совещания, п. 3 | C5: «Обсудили верхнеуровневую архитектуру, решили строить централизованную на Asterisk с выносами в кластерах. По плану первый этап все за исключением Воронежа, далее Воронеж.» Уточнение: центр размещается в московском ЦОД, на обеих площадках живые узлы; остальные узлы по городам.
A6: Архитектура | B6: центр в ЦОД + выносы | C6: Центр — московский ЦОД: ДВА ЖИВЫХ УЗЛА в разных залах. Оба обслуживают вызовы, московские 80 абонентов поделены поровну и прописаны друг другу резервными. Панель управления FreePBX включена только на ЦОД-1. Выносы — Ростов, Ставрополь, Нижний Новгород, Славянск-на-Кубани, Воронеж — работают узлами того же кластера: локальная регистрация телефонов и свой выход в город, при отказе площадки телефоны уходят в ЦОД.
A7: Стойки в ЦОД | B7: наши, залы независимы | C7: Два узла в ЦОД действительно резервируют друг друга, а не стоят за одним вводом питания. Это условие, без которого схема резервирования не имела бы смысла.
A8: Ждать никого не нужно | B8: да | C8: Площадки наши, адреса известны, стойки в ЦОД наши, SIP-пользователей ВАТС заводим сами, ПО бесплатное, машины на своей виртуализации. Закупок и внешних согласований в плане нет. Практический вывод: если график поедет, причина будет внутренней — не хватило людей, не согласовали окно, не успели с перенумерацией.
A9: Дата начала работ | B9: 46272 | C9: ДОПУЩЕНИЕ. Понедельник. Отсчёт идёт от старта работ, то есть от стадии «проект открыт». Стадии 0–4 воронки плана автоматизации (постановка задачи, оценка, согласование карточки, ВЕ, приказа) в эти 15 недель не входят и идут до них.
A10: Длительность, недель | B10: 16 | C10: Два этапа подряд: 11 недель без Воронежа + 4 недели Воронеж. Этапы последовательны по решению совещания, совмещать нельзя.
A11: Дата завершения работ | B11: 46381 | C11: Дата начала + 15 недель, последний рабочий день
A12: ЭТАП 1 — центр в ЦОД + все выносы, кроме Воронежа | B12: недели 1–12, 810 абонентов | C12: ЦОД-1 40 и ЦОД-2 40, Ростов 352, Ставрополь 74, Нижний Новгород 164, Славянск-на-Кубани 140.
A13: ЭТАП 2 — Воронеж | B13: недели 13–16, 445 абонентов | C13: Воронеж 229, Мясокомбинат 187, Калуга 29.
A14: Ставрополь получает свою АТС | B14: да, задача 8.2 | C14: Раньше его 74 абонента висели на ростовском сервере и зависели от канала до Ростова. Своя АТС даёт им локальную живучесть и попутно делает число узлов нечётным.
A15: Порядок переноса центра | B15: Ростов → ЦОД-1 → +ЦОД-2 | C15: Вся боевая база сейчас на ростовской АТС. Сначала она вводится в кластер как первый узел (задача 4), затем клонируется в ЦОД-1 и роль мастера передаётся туда, затем ЦОД-1 клонируется в ЦОД-2 (задача 5). Ростов после этого — обычный вынос со своими 352 абонентами. Переустановки нет ни на одном шаге, откат — возврат роли на Ростов.
A16: Пилотный вынос | B16: Ставрополь | C16: Порядок ввода выносов: Ставрополь (пилот), затем Нижний Новгород, затем Славянск-на-Кубани. ВАЖНО ПОНИМАТЬ: у Ставрополя нет своей станции — его 74 абонента уже в общей базе, поэтому пилот проверяет кластер, каналы и провижининг, но НЕ проверяет перенос действующей АТС с её гашением. Эта часть процедуры впервые отрабатывается на Нижнем Новгороде (задача 8.1) — её стоит пройти с тем же вниманием, что и пилот.
A17: Оповещение техподдержки | B17: задача 3 | C17: До начала работ согласован порядок: кто и по какому каналу поднимается по тревоге, за какое время и что считается инцидентом. Порядок роздан всем участникам работ — иначе в первую же нештатную ситуацию искать будет некого.
A18: КОМАНДА ПРОЕКТА | B18: четыре человека
A19: Руководитель | B19: Савенко В. | C19: Главный по проекту, указан заказчиком во всех строках плана.
A20: Основной исполнитель | B20: Цеховской В. | C20: Инженер кластера. Задачи 1–9 и 12 — вся работа с кластером, переносом центра и вводом выносов.
A21: Помощник | B21: Кириевская Е. | C21: Задачи 10, 11, 13, 14 — консолидация мелких АТС и перенумерация. Частичная занятость, идут параллельно основным работам.
A22: Развёртывание и адресация | B22: Дулепов А. | C22: Создание клонов, установка и присвоение IP-адресов на площадках. Проставлен исполнителем в соответствующих подзадачах.
A23: Трудозатраты всего, ч-д | B23: 100 | C23: Сумма по задачам, см. лист плана
A24: в том числе инженер кластера | B24: 70 | C24: Задачи 1–7 и 10. Помещается в 15 недель × 5 дней = 75 ч-д одного человека.
A25: в том числе второй исполнитель | B25: 30 | C25: Задачи 8, 9, 11, 12 — консолидация мелких АТС и перенумерация. Работа организационная, идёт параллельно силами второго человека с частичной занятостью. Одним инженером весь объём в срок не выполняется — это ограничение плана, а не оценка.
A26: Внутренняя ставка, ₽/ч-д | B26: 11515 | C26: Из формулы =11515*M4 в файле «План работ ДИТ 2023.xlsx», колонка «Плановая себестоимость внутренних затрат».
A27: Плановая себестоимость внутренних затрат, ₽ без НДС | B27: =B23*B26 -> 1151500 | C27: Трудозатраты × ставка, рассчитывается формулой
A28: Плановая себестоимость внешних затрат, ₽ без НДС | B28: 0 | C28: Всё программное обеспечение бесплатное: MariaDB Galera, Asterisk, FreePBX, OSS PBX End Point Manager. Все узлы — свои виртуальные машины, закупки нет.
A29: Абонентов в периметре | B29: 1255 | C29: Аудит 12 станций, docs/plan/numbering-plan.csv
A30: Станций сейчас | B30: 12 | C30: Там же
A31: Узлов кластера после внедрения | B31: 7 | C31: ЦОД-1 40 и ЦОД-2 40 (оба живые), Ростов 352, Ставрополь 74, Нижний Новгород 164, Славянск-на-Кубани 140, Воронеж 445. Итого 1255 — сходится с аудитом.
A32: Голосов в кворуме | B32: 7 | C32: Семь узлов — число НЕЧЁТНОЕ, поэтому арбитр не нужен вообще. Кластер переживает потерю трёх узлов и остаётся работоспособным при потере московского ЦОД целиком: у городов остаётся 5 голосов из 7.
A33: Арбитр garbd | B33: не нужен | C33: В прежней версии плана Ставрополь оставался на ростовском сервере, узлов было шесть, и чётность приходилось добирать арбитром. Собственная АТС в Ставрополе делает число нечётным — та же виртуальная машина вместо бесполезного голоса несёт 74 абонента.
A34: Кворум в конце этапа 1 | B34: 6 | C34: ВНИМАНИЕ. Без Воронежа узлов шесть — число чётное. Держится недели 11–12, закрывается вводом Воронежа. Если даже две недели такого состояния неприемлемы, на этот период ставится временный арбитр garbd.
A35: Виртуальных машин добавить | B35: 3 | C35: ЦОД-1, ЦОД-2 и Ставрополь. Все — свои мощности, закупки нет. У четырёх остальных площадок машины уже есть.
A36: Размещение ВМ по хостам | B36: проверить | C36: КРИТИЧНО. Узлы обязаны стоять на разных физических хостах: пять ВМ на одном гипервизоре — это не отказоустойчивый кластер, а пять копий одной точки отказа. Проверяется на этапе 1 до ввода второго узла.
A37: Снимки ВМ как резервная копия | B37: нельзя | C37: Откат узла на снимок возвращает его с устаревшим seqno. Такой узел вводится обратно только через prepare-clone.sh --full-resync. Резервные копии снимаются на уровне базы (mysqldump), а не гипервизора.
A38: Оба узла ЦОД — живые | B38: да | C38: ЦОД-2 не пассивная копия: он несёт вызовы наравне с ЦОД-1. Резерв, который никогда не берёт нагрузку, не проверен — поэтому 80 московских абонентов делятся по 40 на зал, и каждый зал прописан другому резервным. Отказ зала проверяется реальным трафиком, а не инструкцией.
A39: Панель управления FreePBX | B39: ровно на одном узле | C39: Живой Asterisk — не второй FreePBX. Две включённые панели пишут в общую базу наперегонки. На ЦОД-2 FreePBX установлен (он клон) и выключен — включается за минуты. Переключение отрабатывается учебно в задаче 8.
A40: Неделя 16 — предновогодняя | B40: 21–25 декабря | C40: ВНИМАНИЕ. На эту неделю приходится завершение перенумерации Воронежа. Люди в отпусках, проверять изменения некому. Либо старт сдвигается на неделю раньше, либо задача 13 переносится на январь.
A42: Что нужно заполнить вручную
A43: Номер приказа / внутреннего проекта | C43: Присваивается при открытии проекта.
A44: Дата протокола совещания | C44: Проставить дату документа, из которого взята этапность.
A45: Адресный план узлов | C45: Проставить IP семи узлов: ЦОД-1, ЦОД-2, Ростов, Ставрополь, Нижний Новгород, Славянск-на-Кубани, Воронеж.
A47: Жёлтой заливкой отмечены ячейки, которые заполняются вручную.

Sheet План работ
B1: Централизованная телефония на Asterisk: центр в московском ЦОД (два зала), выносы — Ростов, Ставрополь, Нижний Новгород, Славянск-на-Кубани, Воронеж | P1: Сентябрь 2026 | T1: Октябрь 2026 | X1: Ноябрь 2026 | AC1: Декабрь 2026
A2: № | B2: Название задачи | C2: Категория активности | D2: Программа | E2: Заказчик | F2: Плановые сроки начала | G2: Плановые сроки завершения | H2: Фактические/прогнозные сроки завершения | I2: Проблема | J2: Результат | K2: Исполнитель | L2: Статус | M2: ТРЗ, ч/д | N2: Плановая себестоимость внутренних затрат (ТРЗ), руб. без НДС | O2: Плановая себестоимость внешних затрат, руб. без НДС | P2: 07-13 | Q2: 14-20 | R2: 21-27 | S2: 28-04 | T2: 05-11 | U2: 12-18 | V2: 19-25 | W2: 26-01 | X2: 02-08 | Y2: 09-15 | Z2: 16-22 | AA2: 23-29 | AB2: 30-06 | AC2: 07-13 | AD2: 14-20 | AE2: 21-27
B3: ЭТАП 1 — центр в московском ЦОД и все выносы, кроме Воронежа (недели 1–12, 810 абонентов)
A4: 1 | B4: Подготовка: ЦОД, сеть, виртуальные машины, договорённости с операторами | C4: развитие | D4: Инфраструктура | E4: Савенко В. | F4: ='Параметры и допущения'!$B$9+0 -> 46272 | G4: ='Параметры и допущения'!$B$9+11 -> 46283 | H4: =G4 -> 46283 | I4: Площадки не связаны между собой сетью; в ЦОД не выделены машины под центральные узлы; у площадок нет отдельных учётных записей SIP для выхода в город | J4: VPN между ЦОД и всеми городами поднят, RTT измерен, в ЦОД выделены две ВМ в разных стойках, у каждой площадки заведён свой SIP-пользователь ВАТС | K4: Цеховской В. | L4: планируется | M4: 8 | N4: ='Параметры и допущения'!$B$26*M4 -> 92120 | O4: 0
A5: 1.1 | B5: Утвердить единый план нумерации, разослать сотрудникам новые номера | F5: ='Параметры и допущения'!$B$9+0 -> 46272 | G5: ='Параметры и допущения'!$B$9+4 -> 46276 | J5: План нумерации утверждён, уведомления разосланы | K5: Цеховской В. | L5: планируется | M5: 1
A6: 1.2 | B6: Организовать site-to-site VPN: ЦОД — города | F6: ='Параметры и допущения'!$B$9+0 -> 46272 | G6: ='Параметры и допущения'!$B$9+11 -> 46283 | J6: Сеть между ЦОД и всеми площадками работает | K6: Цеховской В. | L6: планируется | M6: 2
A7: 1.3 | B7: Замерить RTT и потери: ЦОД — каждый город и между залами ЦОД | F7: ='Параметры и допущения'!$B$9+7 -> 46279 | G7: ='Параметры и допущения'!$B$9+11 -> 46283 | J7: Замеры выполнены; площадки с RTT выше 50 мс исключены из синхронной репликации | K7: Цеховской В. | L7: планируется | M7: 1
A8: 1.4 | B8: Собрать адресный план на семь узлов | F8: ='Параметры и допущения'!$B$9+0 -> 46272 | G8: ='Параметры и допущения'!$B$9+4 -> 46276 | J8: Адреса всех площадок известны, план зафиксирован | K8: Дулепов А. | L8: планируется | M8: 1
A9: 1.5 | B9: Выделить три ВМ: две в ЦОД (разные стойки) и одну под Ставрополь | F9: ='Параметры и допущения'!$B$9+0 -> 46272 | G9: ='Параметры и допущения'!$B$9+4 -> 46276 | J9: ВМ выделены, узлы разнесены по физическим хостам | K9: Дулепов А. | L9: планируется | M9: 1
A10: 1.6 | B10: Завести SIP-пользователей ВАТС на каждую площадку | F10: ='Параметры и допущения'!$B$9+0 -> 46272 | G10: ='Параметры и допущения'!$B$9+11 -> 46283 | J10: Учётные записи созданы на все площадки, включая Воронеж | K10: Цеховской В. | L10: планируется | M10: 2
A11: 2 | B11: Смена учётных данных и защита периметра | C11: развитие | D11: Инфраструктура | E11: Савенко В. | F11: ='Параметры и допущения'!$B$9+0 -> 46272 | G11: ='Параметры и допущения'!$B$9+11 -> 46283 | H11: =G11 -> 46283 | I11: Учётные данные телефонии не менялись; журнал безопасности Asterisk не ведётся, подбор паролей не отслеживается | J11: Пароли 444 абонентов, транков, AMI и базы данных сменены; включён журнал безопасности и блокировка подбора; восстановление из резервной копии проверено | K11: Цеховской В. | L11: планируется | M11: 10 | N11: ='Параметры и допущения'!$B$26*M11 -> 115150 | O11: 0
A12: 2.1 | B12: Включить журнал безопасности, fail2ban, ограничить доступ к AMI | F12: ='Параметры и допущения'!$B$9+0 -> 46272 | G12: ='Параметры и допущения'!$B$9+4 -> 46276 | J12: Попытки подбора фиксируются и блокируются | K12: Цеховской В. | L12: планируется | M12: 2
A13: 2.2 | B13: Задать порядок идентификации абонентов и перечень кодеков | F13: ='Параметры и допущения'!$B$9+0 -> 46272 | G13: ='Параметры и допущения'!$B$9+4 -> 46276 | J13: Идентификация по учётной записи, alaw первым кодеком | K13: Цеховской В. | L13: планируется | M13: 1
A14: 2.3 | B14: Сменить пароли 444 абонентов | F14: ='Параметры и допущения'!$B$9+0 -> 46272 | G14: ='Параметры и допущения'!$B$9+11 -> 46283 | J14: Пароли сменены | K14: Цеховской В. | L14: планируется | M14: 3
A15: 2.4 | B15: Сменить учётные данные транков, AMI и базы данных | F15: ='Параметры и допущения'!$B$9+7 -> 46279 | G15: ='Параметры и допущения'!$B$9+11 -> 46283 | J15: Учётные данные сменены | K15: Цеховской В. | L15: планируется | M15: 2
A16: 2.5 | B16: Пересобрать конфигурации телефонов | F16: ='Параметры и допущения'!$B$9+7 -> 46279 | G16: ='Параметры и допущения'!$B$9+11 -> 46283 | J16: Телефоны работают с новыми паролями | K16: Цеховской В. | L16: планируется | M16: 1
A17: 2.6 | B17: Проверить восстановление из резервной копии на тестовой машине | F17: ='Параметры и допущения'!$B$9+7 -> 46279 | G17: ='Параметры и допущения'!$B$9+11 -> 46283 | J17: Копия развёрнута и проверена | K17: Цеховской В. | L17: планируется | M17: 1
A18: 3 | B18: Порядок оповещения техподдержки при отклонениях | C18: развитие | D18: Инфраструктура | E18: Савенко В. | F18: ='Параметры и допущения'!$B$9+7 -> 46279 | G18: ='Параметры и допущения'!$B$9+11 -> 46283 | H18: =G18 -> 46283 | I18: Работы идут на боевой телефонии, но не определено, кто поднимается по тревоге и что вообще считается отклонением — договариваться об этом после первой нештатной ситуации поздно | J18: Порядок согласован и роздан всем участникам работ: известны дежурный, канал связи, время реакции и перечень событий, по которым поднимают тревогу | K18: Цеховской В. | L18: планируется | M18: 2 | N18: ='Параметры и допущения'!$B$26*M18 -> 23030 | O18: 0
A19: 3.1 | B19: Определить перечень событий, по которым поднимают тревогу | F19: ='Параметры и допущения'!$B$9+7 -> 46279 | G19: ='Параметры и допущения'!$B$9+11 -> 46283 | J19: Зафиксированы: потеря регистраций на площадке, расхождение узлов кластера, недоступность панели управления, отказ транка в город | K19: Цеховской В. | L19: планируется | M19: 1
A20: 3.2 | B20: Назначить дежурного, канал связи и время реакции; раздать порядок | F20: ='Параметры и допущения'!$B$9+7 -> 46279 | G20: ='Параметры и допущения'!$B$9+11 -> 46283 | J20: У каждого участника работ есть памятка: кому, куда и за какое время сообщать | K20: Цеховской В. | L20: планируется | M20: 1
A21: 4 | B21: Испытательный стенд | C21: развитие | D21: Инфраструктура | E21: Савенко В. | F21: ='Параметры и допущения'!$B$9+14 -> 46286 | G21: ='Параметры и допущения'!$B$9+18 -> 46290 | H21: =G21 -> 46290 | I21: Процедуры восстановления кластера и передачи роли мастера ни разу не выполнялись | J21: Стенд из трёх машин прошёл чек-лист приёмки: клонирование, восстановление кворума и передача роли мастера выполнены руками | K21: Цеховской В. | L21: планируется | M21: 6 | N21: ='Параметры и допущения'!$B$26*M21 -> 69090 | O21: 0
A22: 4.1 | B22: Развернуть тестовый мастер и клонировать его в два узла | F22: ='Параметры и допущения'!$B$9+14 -> 46286 | G22: ='Параметры и допущения'!$B$9+18 -> 46290 | J22: Клоны вступили в кластер, конфликтов имён узлов нет | K22: Дулепов А. | L22: планируется | M22: 3
A23: 4.2 | B23: Отработать передачу роли мастера между двумя узлами | F23: ='Параметры и допущения'!$B$9+14 -> 46286 | G23: ='Параметры и допущения'!$B$9+18 -> 46290 | J23: Процедура выполнена в обе стороны и задокументирована | K23: Цеховской В. | L23: планируется | M23: 2
A24: 4.3 | B24: Отработать восстановление кворума | F24: ='Параметры и допущения'!$B$9+14 -> 46286 | G24: ='Параметры и допущения'!$B$9+18 -> 46290 | J24: Кворум восстановлен вручную | K24: Цеховской В. | L24: планируется | M24: 1
A25: 5 | B25: Ростовская АТС — первый узел кластера | C25: развитие | D25: Инфраструктура | E25: Савенко В. | F25: ='Параметры и допущения'!$B$9+21 -> 46293 | G25: ='Параметры и допущения'!$B$9+25 -> 46297 | H25: =G25 -> 46297 | I25: Вся боевая база живёт на ростовской АТС; перенести её в ЦОД без простоя можно только через кластер | J25: Ростовская АТС работает узлом кластера без переустановки; база готова к репликации в ЦОД | K25: Цеховской В. | L25: планируется | M25: 4 | N25: ='Параметры и допущения'!$B$26*M25 -> 46060 | O25: 0
A26: 5.1 | B26: Снять резервную копию, перевести таблицы и запустить репликацию | F26: ='Параметры и допущения'!$B$9+21 -> 46293 | G26: ='Параметры и допущения'!$B$9+25 -> 46297 | J26: База работает в режиме кластера, число добавочных сошлось | K26: Цеховской В. | L26: планируется | M26: 2
A27: 5.2 | B27: Выгрузить номера в общую базу и проверить | F27: ='Параметры и допущения'!$B$9+21 -> 46293 | G27: ='Параметры и допущения'!$B$9+25 -> 46297 | J27: Абоненты видны из общей базы | K27: Цеховской В. | L27: планируется | M27: 1
A28: 5.3 | B28: Наблюдение до переноса центра | F28: ='Параметры и допущения'!$B$9+21 -> 46293 | G28: ='Параметры и допущения'!$B$9+25 -> 46297 | J28: Отклонений не выявлено | K28: Цеховской В. | L28: планируется | M28: 1
A29: 6 | B29: Центр в московском ЦОД: два живых узла в разных залах | C29: развитие | D29: Инфраструктура | E29: Савенко В. | F29: ='Параметры и допущения'!$B$9+28 -> 46300 | G29: ='Параметры и допущения'!$B$9+39 -> 46311 | H29: =G29 -> 46311 | I29: Управление и база сосредоточены на ростовской АТС — площадке без резервирования; по решению совещания центр переносится в ЦОД с копией во втором зале | J29: Два живых узла в разных залах ЦОД обслуживают вызовы, управление на ЦОД-1; Ростов понижен до выноса, 80 московских абонентов поделены между залами | K29: Цеховской В. | L29: планируется | M29: 10 | N29: ='Параметры и допущения'!$B$26*M29 -> 115150 | O29: 0
A30: 6.1 | B30: Клонировать ростовскую АТС в ЦОД-1, расшить клон в узел | F30: ='Параметры и допущения'!$B$9+28 -> 46300 | G30: ='Параметры и допущения'!$B$9+32 -> 46304 | J30: ЦОД-1 в кластере, синхронизирован | K30: Дулепов А. | L30: планируется | M30: 2
A31: 6.2 | B31: Передать роль мастера с Ростова на ЦОД-1 | F31: ='Параметры и допущения'!$B$9+28 -> 46300 | G31: ='Параметры и допущения'!$B$9+32 -> 46304 | J31: FreePBX и управление работают из ЦОД-1 | K31: Цеховской В. | L31: планируется | M31: 2
A32: 6.3 | B32: Клонировать ЦОД-1 в ЦОД-2 (второй зал), расшить клон в узел | F32: ='Параметры и допущения'!$B$9+35 -> 46307 | G32: ='Параметры и допущения'!$B$9+39 -> 46311 | J32: ЦОД-2 в кластере, узлов три — кворум нечётный | K32: Дулепов А. | L32: планируется | M32: 2
A33: 6.4 | B33: Сделать ЦОД-2 живым узлом: транк оператора, FreePBX оставить выключенным | F33: ='Параметры и допущения'!$B$9+35 -> 46307 | G33: ='Параметры и допущения'!$B$9+39 -> 46311 | J33: ЦОД-2 несёт вызовы наравне с ЦОД-1; панель управления включена ровно на одном узле | K33: Цеховской В. | L33: планируется | M33: 2
A34: 6.5 | B34: Понизить Ростов до выноса, поделить 80 московских абонентов между залами | F34: ='Параметры и допущения'!$B$9+35 -> 46307 | G34: ='Параметры и допущения'!$B$9+39 -> 46311 | J34: По 40 абонентов на зал, каждый зал прописан другому резервным | K34: Цеховской В. | L34: планируется | M34: 2
A35: 7 | B35: Пилотный вынос — Ставрополь | C35: развитие | D35: Инфраструктура | E35: Савенко В. | F35: ='Параметры и допущения'!$B$9+42 -> 46314 | G35: ='Параметры и допущения'!$B$9+53 -> 46325 | H35: =G35 -> 46325 | I35: Схема «центр в ЦОД — вынос в городе» не проверена на реальной нагрузке и канале | J35: Ставрополь работает выносом: локальная регистрация телефонов, свой выход в город, переключение в ЦОД при отказе площадки; его 74 абонента больше не зависят от канала до Ростова | K35: Цеховской В. | L35: планируется | M35: 10 | N35: ='Параметры и допущения'!$B$26*M35 -> 115150 | O35: 0
A36: 7.1 | B36: Клонировать мастер и расшить клон в вынос | F36: ='Параметры и допущения'!$B$9+42 -> 46314 | G36: ='Параметры и допущения'!$B$9+46 -> 46318 | J36: Вынос в кластере | K36: Дулепов А. | L36: планируется | M36: 2
A37: 7.2 | B37: Настроить межузловые транки и перенести диалплан | F37: ='Параметры и допущения'!$B$9+42 -> 46314 | G37: ='Параметры и допущения'!$B$9+46 -> 46318 | J37: Вызовы между ЦОД, Ростовом и Ставрополем проходят | K37: Цеховской В. | L37: планируется | M37: 2
A38: 7.3 | B38: Подключить локальный транк оператора | F38: ='Параметры и допущения'!$B$9+42 -> 46314 | G38: ='Параметры и допущения'!$B$9+46 -> 46318 | J38: Свой выход в город работает | K38: Цеховской В. | L38: планируется | M38: 1
A39: 7.4 | B39: Перевести телефоны на вынос через провижининг | F39: ='Параметры и допущения'!$B$9+42 -> 46314 | G39: ='Параметры и допущения'!$B$9+46 -> 46318 | J39: Телефоны регистрируются в Ставрополе, резервный сервер — ЦОД-1 | K39: Цеховской В. | L39: планируется | M39: 2
A40: 7.5 | B40: Неделя наблюдения под реальной нагрузкой | F40: ='Параметры и допущения'!$B$9+49 -> 46321 | G40: ='Параметры и допущения'!$B$9+53 -> 46325 | J40: Отказ площадки и возврат отработаны, решение о тиражировании принято | K40: Цеховской В. | L40: планируется | M40: 3
A41: 8 | B41: Учебное переключение управления между залами ЦОД | C41: развитие | D41: Инфраструктура | E41: Савенко В. | F41: ='Параметры и допущения'!$B$9+56 -> 46328 | G41: ='Параметры и допущения'!$B$9+60 -> 46332 | H41: =G41 -> 46332 | I41: Вызовы оба зала несут постоянно, но панель управления живёт на одном узле; её переключение не опробовано | J41: Управление переведено в зал 2 и возвращено в зал 1 в согласованное окно; время переключения измерено и внесено в регламент | K41: Цеховской В. | L41: планируется | M41: 3 | N41: ='Параметры и допущения'!$B$26*M41 -> 34545 | O41: 0
A42: 8.1 | B42: Включить FreePBX на ЦОД-2, проверить управление и звонки | F42: ='Параметры и допущения'!$B$9+56 -> 46328 | G42: ='Параметры и допущения'!$B$9+60 -> 46332 | J42: Управление работает из зала 2, вызовы не прерывались | K42: Цеховской В. | L42: планируется | M42: 2
A43: 8.2 | B43: Вернуть управление в ЦОД-1, зафиксировать время переключения | F43: ='Параметры и допущения'!$B$9+56 -> 46328 | G43: ='Параметры и допущения'!$B$9+60 -> 46332 | J43: Схема в штатном состоянии, норматив записан в регламент | K43: Цеховской В. | L43: планируется | M43: 1
A44: 9 | B44: Выносы Нижний Новгород и Славянск-на-Кубани | C44: развитие | D44: Инфраструктура | E44: Савенко В. | F44: ='Параметры и допущения'!$B$9+63 -> 46335 | G44: ='Параметры и допущения'!$B$9+74 -> 46346 | H44: =G44 -> 46346 | I44: Обе площадки обслуживаются отдельными станциями вне кластера; на них впервые отрабатывается полный перенос с гашением старой АТС | J44: Обе площадки работают выносами, старые станции выведены из эксплуатации | K44: Цеховской В. | L44: планируется | M44: 9 | N44: ='Параметры и допущения'!$B$26*M44 -> 103635 | O44: 0
A45: 9.1 | B45: Нижний Новгород — 164 абонента, старая станция гасится | F45: ='Параметры и допущения'!$B$9+63 -> 46335 | G45: ='Параметры и допущения'!$B$9+67 -> 46339 | J45: Вынос работает, станция выведена | K45: Дулепов А. | L45: планируется | M45: 5
A46: 9.2 | B46: Славянск-на-Кубани — 140 абонентов, старая станция гасится | F46: ='Параметры и допущения'!$B$9+70 -> 46342 | G46: ='Параметры и допущения'!$B$9+74 -> 46346 | J46: Вынос работает, станция выведена; этап 1 закрыт | K46: Дулепов А. | L46: планируется | M46: 4
A47: 10 | B47: Консолидация мелких АТС этапа 1 | C47: развитие | D47: Инфраструктура | E47: Савенко В. | F47: ='Параметры и допущения'!$B$9+49 -> 46321 | G47: ='Параметры и допущения'!$B$9+74 -> 46346 | H47: =G47 -> 46346 | I47: Шесть станций на 127 абонентов дорого поддерживать и невыгодно включать в кластер отдельными узлами | J47: Абоненты мелких станций переведены на выносы и в ЦОД, станции выведены из эксплуатации | K47: Кириевская Е. | L47: планируется | M47: 6 | N47: ='Параметры и допущения'!$B$26*M47 -> 69090 | O47: 0
A48: 10.1 | B48: Манитек, Семикаракорский, Цимлянский, Приманыческий — 73 абонента — в Ростов | F48: ='Параметры и допущения'!$B$9+49 -> 46321 | G48: ='Параметры и допущения'!$B$9+60 -> 46332 | J48: Станции выведены | K48: Кириевская Е. | L48: планируется | M48: 3
A49: 10.2 | B49: ССЗ — 39 абонентов — в Нижний Новгород | F49: ='Параметры и допущения'!$B$9+70 -> 46342 | G49: ='Параметры и допущения'!$B$9+74 -> 46346 | J49: Станция выведена | K49: Кириевская Е. | L49: планируется | M49: 2
A50: 10.3 | B50: Локальный PBX — 15 абонентов — в ЦОД | F50: ='Параметры и допущения'!$B$9+77 -> 46349 | G50: ='Параметры и допущения'!$B$9+81 -> 46353 | J50: Станция выведена | K50: Кириевская Е. | L50: планируется | M50: 1
A51: 11 | B51: Перевод абонентов этапа 1 на единый план нумерации | C51: развитие | D51: Инфраструктура | E51: Савенко В. | F51: ='Параметры и допущения'!$B$9+35 -> 46307 | G51: ='Параметры и допущения'!$B$9+81 -> 46353 | H51: =G51 -> 46353 | I51: Станции используют пересекающиеся номера, единый план невозможен без разведения конфликтов | J51: 810 абонентов этапа 1 переведены на пятизначную нумерацию, переадресации сняты | K51: Кириевская Е. | L51: планируется | M51: 12 | N51: ='Параметры и допущения'!$B$26*M51 -> 138180 | O51: 0
A52: 11.1 | B52: Ростов и его мелкие площадки — 352 абонента | F52: ='Параметры и допущения'!$B$9+35 -> 46307 | G52: ='Параметры и допущения'!$B$9+60 -> 46332 | J52: Площадки переведены | K52: Кириевская Е. | L52: планируется | M52: 4
A53: 11.2 | B53: Ставрополь — 74 абонента | F53: ='Параметры и допущения'!$B$9+49 -> 46321 | G53: ='Параметры и допущения'!$B$9+60 -> 46332 | J53: Площадка переведена | K53: Кириевская Е. | L53: планируется | M53: 1
A54: 11.3 | B54: Нижний Новгород и ССЗ — 164 абонента | F54: ='Параметры и допущения'!$B$9+63 -> 46335 | G54: ='Параметры и допущения'!$B$9+81 -> 46353 | J54: Площадки переведены | K54: Кириевская Е. | L54: планируется | M54: 3
A55: 11.4 | B55: Славянск-на-Кубани — 140 абонентов | F55: ='Параметры и допущения'!$B$9+70 -> 46342 | G55: ='Параметры и допущения'!$B$9+81 -> 46353 | J55: Площадка переведена | K55: Кириевская Е. | L55: планируется | M55: 2
A56: 11.5 | B56: Москва — 80 абонентов, снятие переадресаций | F56: ='Параметры и допущения'!$B$9+63 -> 46335 | G56: ='Параметры и допущения'!$B$9+81 -> 46353 | J56: Площадка переведена | K56: Кириевская Е. | L56: планируется | M56: 2
B57: ЭТАП 2 — Воронеж (недели 13–16, 445 абонентов)
A58: 12 | B58: Воронежский вынос | C58: развитие | D58: Инфраструктура | E58: Савенко В. | F58: ='Параметры и допущения'!$B$9+84 -> 46356 | G58: ='Параметры и допущения'!$B$9+95 -> 46367 | H58: =G58 -> 46367 | I58: Воронеж — самая крупная площадка (445 абонентов) и по решению совещания вводится отдельным этапом после всех остальных | J58: Воронеж работает выносом; узлов семь — число нечётное, кворум не требует арбитра | K58: Цеховской В. | L58: планируется | M58: 8 | N58: ='Параметры и допущения'!$B$26*M58 -> 92120 | O58: 0
A59: 12.1 | B59: Проверить, что все шесть узлов Synced до начала работ | F59: ='Параметры и допущения'!$B$9+84 -> 46356 | G59: ='Параметры и допущения'!$B$9+88 -> 46360 | J59: Кластер здоров, расхождений нет | K59: Цеховской В. | L59: планируется | M59: 1
A60: 12.2 | B60: Клонировать мастер и расшить клон в вынос | F60: ='Параметры и допущения'!$B$9+84 -> 46356 | G60: ='Параметры и допущения'!$B$9+88 -> 46360 | J60: Вынос в кластере | K60: Дулепов А. | L60: планируется | M60: 2
A61: 12.3 | B61: Межузловые транки и диалплан | F61: ='Параметры и допущения'!$B$9+84 -> 46356 | G61: ='Параметры и допущения'!$B$9+88 -> 46360 | J61: Вызовы с другими площадками проходят | K61: Цеховской В. | L61: планируется | M61: 2
A62: 12.4 | B62: Локальный транк оператора | F62: ='Параметры и допущения'!$B$9+91 -> 46363 | G62: ='Параметры и допущения'!$B$9+95 -> 46367 | J62: Свой выход в город работает | K62: Цеховской В. | L62: планируется | M62: 1
A63: 12.5 | B63: Перевести телефоны на вынос через провижининг | F63: ='Параметры и допущения'!$B$9+91 -> 46363 | G63: ='Параметры и допущения'!$B$9+95 -> 46367 | J63: Телефоны регистрируются в Воронеже, резервный сервер — ЦОД-1 | K63: Цеховской В. | L63: планируется | M63: 2
A64: 13 | B64: Консолидация воронежских АТС | C64: развитие | D64: Инфраструктура | E64: Савенко В. | F64: ='Параметры и допущения'!$B$9+91 -> 46363 | G64: ='Параметры и допущения'!$B$9+102 -> 46374 | H64: =G64 -> 46374 | I64: Мясокомбинат и Калуга — 216 абонентов на двух отдельных станциях | J64: Абоненты переведены на воронежский вынос, станции выведены из эксплуатации | K64: Кириевская Е. | L64: планируется | M64: 6 | N64: ='Параметры и допущения'!$B$26*M64 -> 69090 | O64: 0
A65: 13.1 | B65: Мясокомбинат — 187 абонентов | F65: ='Параметры и допущения'!$B$9+91 -> 46363 | G65: ='Параметры и допущения'!$B$9+102 -> 46374 | J65: Станция выведена | K65: Кириевская Е. | L65: планируется | M65: 4
A66: 13.2 | B66: Калуга — 29 абонентов | F66: ='Параметры и допущения'!$B$9+98 -> 46370 | G66: ='Параметры и допущения'!$B$9+102 -> 46374 | J66: Станция выведена | K66: Кириевская Е. | L66: планируется | M66: 2
A67: 14 | B67: Перевод воронежских абонентов на единый план нумерации | C67: развитие | D67: Инфраструктура | E67: Савенко В. | F67: ='Параметры и допущения'!$B$9+91 -> 46363 | G67: ='Параметры и допущения'!$B$9+109 -> 46381 | H67: =G67 -> 46381 | I67: 445 абонентов Воронежа и его станций используют старую нумерацию | J67: Воронеж переведён на пятизначную нумерацию, переадресации со старых номеров сняты | K67: Кириевская Е. | L67: планируется | M67: 6 | N67: ='Параметры и допущения'!$B$26*M67 -> 69090 | O67: 0
A68: 14.1 | B68: Воронеж и Мясокомбинат — 416 абонентов | F68: ='Параметры и допущения'!$B$9+91 -> 46363 | G68: ='Параметры и допущения'!$B$9+109 -> 46381 | J68: Площадки переведены | K68: Кириевская Е. | L68: планируется | M68: 5
A69: 14.2 | B69: Калуга — сверка: часть абонентов уже на пятизначных | F69: ='Параметры и допущения'!$B$9+105 -> 46377 | G69: ='Параметры и допущения'!$B$9+109 -> 46381 | J69: Расхождений нет, переадресации сняты | K69: Кириевская Е. | L69: планируется | M69: 1
B70: ИТОГО по проекту | M70: =M4+M11+M18+M21+M25+M29+M35+M41+M44+M47+M51+M58+M64+M67 -> 100 | N70: =N4+N11+N18+N21+N25+N29+N35+N41+N44+N47+N51+N58+N64+N67 -> 1151500 | O70: =O4+O11+O18+O21+O25+O29+O35+O41+O44+O47+O51+O58+O64+O67 -> 0
